datadog_healthcheck_deployer/__init__.py
datadog_healthcheck_deployer/cli.py
datadog_healthcheck_deployer/config.py
datadog_healthcheck_deployer/core.py
datadog_healthcheck_deployer/checks/base.py
datadog_healthcheck_deployer/checks/dns.py
datadog_healthcheck_deployer/checks/http.py
datadog_healthcheck_deployer/checks/ssl.py
datadog_healthcheck_deployer/checks/tcp.py
datadog_healthcheck_deployer/dashboards/__init__.py
datadog_healthcheck_deployer/dashboards/dashboard.py
datadog_healthcheck_deployer/dashboards/manager.py
datadog_healthcheck_deployer/monitors/__init__.py
datadog_healthcheck_deployer/monitors/manager.py
datadog_healthcheck_deployer/monitors/monitor.py
datadog_healthcheck_deployer/utils/__init__.py
datadog_healthcheck_deployer/utils/constants.py
datadog_healthcheck_deployer/utils/exceptions.py
datadog_healthcheck_deployer/utils/logging.py
datadog_healthcheck_deployer/utils/utils.py
datadog_healthcheck_deployer/utils/validation.py
datadog_healthcheck_deployer/validators/__init__.py
datadog_healthcheck_deployer/validators/base.py
datadog_healthcheck_deployer/validators/check_validator.py
datadog_healthcheck_deployer/validators/config_validator.py
datadog_healthcheck_deployer/validators/dashboard_validator.py
datadog_healthcheck_deployer/validators/monitor_validator.py
datadog_healthcheck_deployer-0.1.0.dist-info/LICENSE
datadog_healthcheck_deployer-0.1.0.dist-info/METADATA
datadog_healthcheck_deployer-0.1.0.dist-info/WHEEL
datadog_healthcheck_deployer-0.1.0.dist-info/entry_points.txt
datadog_healthcheck_deployer-0.1.0.dist-info/top_level.txt
datadog_healthcheck_deployer-0.1.0.dist-info/RECORD
