Metadata-Version: 2.2
Name: datadog-healthcheck-deployer
Version: 0.1.0
Summary: A tool for deploying and managing DataDog health checks using configuration as code
Author-email: fleXRPL <info@flexrpl.com>
License: MIT
Project-URL: Homepage, https://github.com/fleXRPL/datadog-healthcheck-deployer
Project-URL: Documentation, https://github.com/fleXRPL/datadog-healthcheck-deployer/wiki
Project-URL: Repository, https://github.com/fleXRPL/datadog-healthcheck-deployer.git
Project-URL: Issues, https://github.com/fleXRPL/datadog-healthcheck-deployer/issues
Classifier: Development Status :: 4 - Beta
Classifier: Intended Audience :: Developers
Classifier: Intended Audience :: System Administrators
Classifier: License :: OSI Approved :: MIT License
Classifier: Operating System :: OS Independent
Classifier: Programming Language :: Python :: 3
Classifier: Programming Language :: Python :: 3.8
Classifier: Programming Language :: Python :: 3.9
Classifier: Programming Language :: Python :: 3.10
Classifier: Programming Language :: Python :: 3.11
Classifier: Programming Language :: Python :: 3.12
Classifier: Topic :: Software Development :: Libraries :: Python Modules
Classifier: Topic :: System :: Monitoring
Requires-Python: >=3.8
License-File: LICENSE
Requires-Dist: datadog>=0.44.0
Requires-Dist: pyyaml>=6.0
Requires-Dist: click>=8.0
Requires-Dist: requests>=2.26.0
Requires-Dist: jsonschema>=4.0.0
Requires-Dist: typing-extensions>=4.0.0
Provides-Extra: dev
Requires-Dist: pytest>=7.0.0; extra == "dev"
Requires-Dist: pytest-cov>=4.0.0; extra == "dev"
Requires-Dist: pytest-mock>=3.10.0; extra == "dev"
Requires-Dist: pytest-asyncio>=0.21.0; extra == "dev"
Requires-Dist: black>=22.0.0; extra == "dev"
Requires-Dist: isort>=5.0.0; extra == "dev"
Requires-Dist: flake8>=4.0.0; extra == "dev"
Requires-Dist: mypy>=0.950; extra == "dev"
Requires-Dist: pylint>=2.17.0; extra == "dev"
Requires-Dist: bandit>=1.7.0; extra == "dev"
Requires-Dist: pre-commit>=2.17.0; extra == "dev"
